pyult/__init__.py
pyult/__main__.py
pyult/dataframe.py
pyult/file.py
pyult/general.py
pyult/image.py
pyult/ncspline.py
pyult/recording.py
pyult/session.py
pyult-0.2.1.dist-info/LICENSE.txt
pyult-0.2.1.dist-info/METADATA
pyult-0.2.1.dist-info/WHEEL
pyult-0.2.1.dist-info/top_level.txt
pyult-0.2.1.dist-info/RECORD
